{
  "version": 2,
  "data": {
    "lastSaved": "0001-01-01T00:00:00Z",
    "patchVersion": 0,
    "collectedTokens": 400,
    "currentTimeSlotId": "season_S74",
    "rewardsThisSeason": [
      {
        "tierIndex": 0,
        "mainRewardStatus": [
          2
        ]
      },
      {
        "tierIndex": 1,
        "mainRewardStatus": [
          2
        ]
      },
      {
        "tierIndex": 2,
        "mainRewardStatus": [
          2
        ]
      },
      {
        "tierIndex": 3,
        "mainRewardStatus": [
          2
        ]
      },
      {
        "tierIndex": 4,
        "mainRewardStatus": [
          2
        ]
      },
      {
        "tierIndex": 5,
        "mainRewardStatus": [
          2
        ]
      },
      {
        "tierIndex": 6,
        "mainRewardStatus": [
          2
        ]
      },
      {
        "tierIndex": 7,
        "mainRewardStatus": [
          2
        ]
      },
      {
        "tierIndex": 8,
        "mainRewardStatus": [
          2
        ]
      },
      {
        "tierIndex": 9,
        "mainRewardStatus": [
          2
        ]
      },
      {
        "tierIndex": 10,
        "mainRewardStatus": [
          2
        ]
      },
      {
        "tierIndex": 11,
        "mainRewardStatus": [
          2
        ]
      },
      {
        "tierIndex": 12,
        "mainRewardStatus": [
          2
        ]
      },
      {
        "tierIndex": 13,
        "mainRewardStatus": [
          2
        ]
      },
      {
        "tierIndex": 14,
        "mainRewardStatus": [
          2
        ]
      },
      {
        "tierIndex": 15,
        "mainRewardStatus": [
          2
        ]
      },
      {
        "tierIndex": 16,
        "mainRewardStatus": [
          2
        ]
      },
      {
        "tierIndex": 17,
        "mainRewardStatus": [
          2
        ]
      },
      {
        "tierIndex": 18,
        "mainRewardStatus": [
          2
        ]
      },
      {
        "tierIndex": 19,
        "mainRewardStatus": [
          2
        ]
      },
      {
        "tierIndex": 20,
        "mainRewardStatus": [
          1
        ]
      },
      {
        "tierIndex": 21,
        "mainRewardStatus": [
          2
        ]
      },
      {
        "tierIndex": 22,
        "mainRewardStatus": [
          2
        ]
      },
      {
        "tierIndex": 23,
        "mainRewardStatus": [
          2
        ]
      },
      {
        "tierIndex": 24,
        "mainRewardStatus": [
          2
        ]
      },
      {
        "tierIndex": 25,
        "mainRewardStatus": [
          2
        ]
      },
      {
        "tierIndex": 26,
        "mainRewardStatus": [
          2
        ]
      },
      {
        "tierIndex": 27,
        "mainRewardStatus": [
          2
        ]
      },
      {
        "tierIndex": 28,
        "mainRewardStatus": [
          2
        ]
      },
      {
        "tierIndex": 29,
        "mainRewardStatus": [
          2
        ]
      },
      {
        "tierIndex": 30,
        "mainRewardStatus": [
          2
        ]
      }
    ],
    "shownNewSeasonPopup": true,
    "lastUnlockedTierSeen": 31,
    "hasClaimedSeasonHuntReward": true,
    "unlockedRewardTime": "0001-01-01T00:00:00Z"
  }
}
