{
  "version": 1,
  "data": {
    "lastSaved": "0001-01-01T00:00:00Z",
    "updateAppViewLastSeen": "0001-01-01T00:00:00Z",
    "ftuePopupsSeen": [],
    "lastSeenDailyEvent": "",
    "newSeasonPopupShownForID": null,
    "localMailsSeen": {
      "s84_subwayclassic_welcome": true,
      "s84_subwayclassic_player_profile": true,
      "s84_subwayclassic_birthday_2024": true,
      "s84_subwayclassic_survey_ios": true,
      "s84_subwayclassic_survey_android": true,
      "s84_subwayclassic_season_challenge_1": true,
      "s84_subwayclassic_onerun_challenge": true,
      "s84_subwayclassic_floorislava_1": true,
      "s84_subwayclassic_plant_invasion": true,
      "s84_subwayclassic_seasonhunt": true,
      "s84_subwayclassic_ec": true,
      "s84_subwayclassic_season_challenge_2": true,
      "s84_subwayclassic_challenges": true,
      "s84_subwayclassic_next_season": true,
      "s84_subwayclassic_updateGame_ios": true,
      "s84_subwayclassic_updateGame_google": true,
      "s84_subwayclassic_updateGame_amazon": true
    },
    "lastSeenTooltipIds": {},
    "popupSeenInfo": {},
    "lastSeenPopupTime": "0001-01-01T00:00:00Z",
    "promotionsSeenInfo": {},
    "challengesSeenData": {},
    "revealedChallenges": {}
  }
}