{
  "version": 1,
  "data": {
    "lastSaved": "0001-01-01T00:00:00Z",
    "updateAppViewLastSeen": "0001-01-01T00:00:00Z",
    "ftuePopupsSeen": [],
    "lastSeenDailyEvent": "",
    "newSeasonPopupShownForID": null,
    "localMailsSeen": {
      "s88_neworleans_welcome": true,
      "s88_neworleans_season_challenge_1": true,
      "s88_neworleans_mailbox_indonesia_independence": true,
      "s88_neworleans_mailbox_india_independence": true,
      "s88_neworleans_craft_character_1": true,
      "s88_neworleans_craft_character_2": true,
      "s86_hollywood_green_moves": true,
      "s88_neworleans_onerun": true,
      "s88_neworleans_floorislava_1": true,
      "s88_neworleans_plant_invasion": true,
      "s88_neworleans_seasonhunt": true,
      "s88_neworleans_ec": true,
      "s88_neworleans_season_challenge_2": true,
      "s88_neworleans_challenges": true,
      "s88_neworleans_next_season": true,
      "s88_neworleans_updateGame_ios": true,
      "s88_neworleans_updateGame_google": true,
      "s88_neworleans_updateGame_amazon": true
    },
    "lastSeenTooltipIds": {},
    "popupSeenInfo": {},
    "lastSeenPopupTime": "0001-01-01T00:00:00Z",
    "promotionsSeenInfo": {},
    "challengesSeenData": {},
    "revealedChallenges": {}
  }
}